{
    "bits": [
        {
            "bit": 0,
            "location": [
                2644,
                2528
            ],
            "radius": 10
        },
        {
            "bit": 1,
            "location": [
                2594,
                2620
            ],
            "radius": 10
        },
        {
            "bit": 2,
            "location": [
                2526,
                2709
            ],
            "radius": 10
        },
        {
            "bit": 3,
            "location": [
                2441,
                2760
            ],
            "radius": 10
        },
        {
            "bit": 4,
            "location": [
                2329,
                2792
            ],
            "radius": 10
        },
        {
            "bit": 5,
            "location": [
                2221,
                2800
            ],
            "radius": 10
        },
        {
            "bit": 6,
            "location": [
                1870,
                2563
            ],
            "radius": 10
        },
        {
            "bit": 7,
            "location": [
                1828,
                2453
            ],
            "radius": 10
        },
        {
            "bit": 8,
            "location": [
                1820,
                2352
            ],
            "radius": 10
        },
        {
            "bit": 9,
            "location": [
                1832,
                2255
            ],
            "radius": 10
        },
        {
            "bit": 10,
            "location": [
                1868,
                2153
            ],
            "radius": 10
        },
        {
            "bit": 11,
            "location": [
                1919,
                2077
            ],
            "radius": 10
        },
        {
            "bit": 12,
            "location": [
                2010,
                2014
            ],
            "radius": 10
        },
        {
            "bit": 13,
            "location": [
                2114,
                1971
            ],
            "radius": 10
        },
        {
            "bit": 14,
            "location": [
                2211,
                1961
            ],
            "radius": 10
        },
        {
            "bit": 15,
            "location": [
                2606,
                2193
            ],
            "radius": 10
        },
        {
            "bit": 16,
            "location": [
                2645,
                2293
            ],
            "radius": 10
        },
        {
            "bit": 17,
            "location": [
                2661,
                2413
            ],
            "radius": 10
        }
    ],
    "coding": "gray"
}